kubera/__init__.py
kubera/_version.py
kubera/chatgpt/extract_stats.py
kubera/chatgpt/extract_trace.py
kubera/claude_code/__init__.py
kubera/claude_code/extract_stats.py
kubera/claude_code/extract_trace.py
kubera/claude_web/extract_stats.py
kubera/claude_web/extract_trace.py
kubera-0.0.1.dist-info/licenses/LICENSE
kubera-0.0.1.dist-info/METADATA
kubera-0.0.1.dist-info/WHEEL
kubera-0.0.1.dist-info/entry_points.txt
kubera-0.0.1.dist-info/top_level.txt
kubera-0.0.1.dist-info/RECORD
