Metadata-Version: 2.4
Name: kubera
Version: 0.0.1
Summary: Kubera is a tool for annonymizing and extracting traces from from ChatGPT, Claude, etc. usage data
Author: Vajra Team
Maintainer: Vajra Team
License-Expression: Apache-2.0
Project-URL: Homepage, https://github.com/project-vajra/kubera
Project-URL: Repository, https://github.com/project-vajra/kubera
Project-URL: Bug Tracker, https://github.com/project-vajra/kubera/issues
Keywords: data-extraction,data-anonymization,chatgpt,claude,openai,gpt
Classifier: Development Status :: 4 - Beta
Classifier: Intended Audience :: Developers
Classifier: Intended Audience :: Science/Research
Classifier: Operating System :: OS Independent
Classifier: Programming Language :: Python :: 3
Classifier: Programming Language :: Python :: 3.12
Requires-Python: >=3.12
License-File: LICENSE
Requires-Dist: numpy>=1.21.0
Requires-Dist: pandas>=1.3.0
Requires-Dist: transformers>=4.21.0
Requires-Dist: humanize>=4.0.0
Provides-Extra: dev
Requires-Dist: pytest>=6.0; extra == "dev"
Requires-Dist: pytest-cov; extra == "dev"
Requires-Dist: pytest-html; extra == "dev"
Requires-Dist: pytest-xdist; extra == "dev"
Requires-Dist: coverage[toml]; extra == "dev"
Requires-Dist: black; extra == "dev"
Requires-Dist: isort; extra == "dev"
Requires-Dist: autoflake; extra == "dev"
Requires-Dist: pyright; extra == "dev"
Requires-Dist: codespell; extra == "dev"
Requires-Dist: pre-commit; extra == "dev"
Provides-Extra: all
Requires-Dist: kubera[dev]; extra == "all"
Dynamic: license-file
